{
  "generator-jhipster": {
    "promptValues": {
      "packageName": "com.chaka.jhipster",
      "nativeLanguage": "fr"
    },
    "jhipsterVersion": "5.0.1",
    "applicationType": "monolith",
    "baseName": "chaka_jhipster_monolith",
    "packageName": "com.chaka.jhipster",
    "packageFolder": "com/chaka/jhipster",
    "serverPort": "8080",
    "authenticationType": "jwt",
    "cacheProvider": "ehcache",
    "enableHibernateCache": true,
    "websocket": false,
    "databaseType": "sql",
    "devDatabaseType": "h2Disk",
    "prodDatabaseType": "mysql",
    "searchEngine": false,
    "messageBroker": false,
    "serviceDiscoveryType": false,
    "buildTool": "maven",
    "enableSwaggerCodegen": false,
    "jwtSecretKey": "c542197754e839ab3f5d73d789a172401967578d",
    "clientFramework": "angularX",
    "useSass": true,
    "clientPackageManager": "yarn",
    "testFrameworks": [],
    "jhiPrefix": "jhi",
    "enableTranslation": true,
    "nativeLanguage": "fr",
    "languages": [
      "fr",
      "en"
    ]
  }
}